filestack/__init__.py
filestack/exceptions.py
filestack/helpers.py
filestack/trafarets.py
filestack/utils.py
filestack/mixins/__init__.py
filestack/mixins/common.py
filestack/mixins/imagetransformation.py
filestack/models/__init__.py
filestack/models/audiovisual.py
filestack/models/client.py
filestack/models/filelink.py
filestack/models/security.py
filestack/models/transformation.py
filestack/uploads/__init__.py
filestack/uploads/external_url.py
filestack/uploads/intelligent_ingestion.py
filestack/uploads/multipart.py
tests/__init__.py
tests/audiovisual_test.py
tests/client_test.py
tests/filelink_test.py
tests/filestack_helpers_test.py
tests/intelligent_ingestion_test.py
tests/multipart_test.py
tests/security_test.py
tests/tasks_test.py
tests/transformation_test.py
tests/utils_test.py
filestack_python-4.0.0.dist-info/LICENSE
filestack_python-4.0.0.dist-info/METADATA
filestack_python-4.0.0.dist-info/WHEEL
filestack_python-4.0.0.dist-info/top_level.txt
filestack_python-4.0.0.dist-info/RECORD
