Metadata-Version: 2.1
Name: filestack-python
Version: 4.0.0
Summary: Filestack Python SDK
Home-page: https://github.com/filestack/filestack-python
Author: filestack.com
Author-email: support@filestack.com
License: Apache 2.0
Classifier: Development Status :: 4 - Beta
Classifier: Intended Audience :: Developers
Classifier: License :: OSI Approved :: Apache Software License
Classifier: Programming Language :: Python
Classifier: Programming Language :: Python :: 3.7
Classifier: Programming Language :: Python :: 3.8
Classifier: Programming Language :: Python :: 3.9
Classifier: Programming Language :: Python :: 3.10
Classifier: Programming Language :: Python :: 3.11
Classifier: Programming Language :: Python :: 3.12
Classifier: Topic :: Internet :: WWW/HTTP
License-File: LICENSE
Requires-Dist: requests>=2.31.0
Requires-Dist: trafaret==2.0.2
